paxb
