Metadata-Version: 1.2
Name: paxb
Version: 0.2.1
Summary: Python Architecture for XML Binding
Home-page: https://github.com/dapper91/paxb
Author: Dmitry Pershin
Author-email: dapper91@mail.ru
License: Public Domain License
Keywords: xml,binding,mapping,serialization,deserialization
Platform: UNKNOWN
Classifier: Development Status :: 4 - Beta
Classifier: Intended Audience :: Developers
Classifier: Natural Language :: English
Classifier: License :: Public Domain
Classifier: Programming Language :: Python
Classifier: Programming Language :: Python :: 3.5
Classifier: Programming Language :: Python :: 3.6
Classifier: Programming Language :: Python :: 3.7
Requires-Python: >=3.5
